scripts/__init__.py
scripts/pull_and_compile_protos.py
tests/__init__.py
tests/test_client/__init__.py
tests/test_client/test_usubscription/__init__.py
tests/test_client/test_usubscription/test_v3/__init__.py
tests/test_client/test_usubscription/test_v3/test_inmemoryusubcriptionclient.py
tests/test_communication/__init__.py
tests/test_communication/mock_utransport.py
tests/test_communication/test_calloptions.py
tests/test_communication/test_inmemoryrpcclient.py
tests/test_communication/test_inmemoryrpcserver.py
tests/test_communication/test_publisher.py
tests/test_communication/test_rpcmapper.py
tests/test_communication/test_rpcresult.py
tests/test_communication/test_simplenotifier.py
tests/test_communication/test_simplepublisher.py
tests/test_communication/test_uclient.py
tests/test_communication/test_upayload.py
tests/test_communication/test_ustatuserror.py
tests/test_transport/__init__.py
tests/test_transport/test_builder/__init__.py
tests/test_transport/test_builder/test_umessagebuilder.py
tests/test_transport/test_utransport.py
tests/test_transport/test_validator/__init__.py
tests/test_transport/test_validator/test_uattributesvalidator.py
tests/test_uri/__init__.py
tests/test_uri/test_factory/__init__.py
tests/test_uri/test_factory/test_uri_factory.py
tests/test_uri/test_serializer/__init__.py
tests/test_uri/test_serializer/test_uriserializer.py
tests/test_uri/test_validator/__init__.py
tests/test_uri/test_validator/test_urivalidator.py
tests/test_uuid/__init__.py
tests/test_uuid/test_factory/__init__.py
tests/test_uuid/test_factory/test_uuidfactory.py
tests/test_uuid/test_factory/test_uuidutils.py
tests/test_uuid/test_validator/__init__.py
tests/test_uuid/test_validator/test_uuidvalidator.py
tests/test_validation/test_validationresult.py
uprotocol/__init__.py
uprotocol/client/README.adoc
uprotocol/client/__init__.py
uprotocol/client/usubscription/__init__.py
uprotocol/client/usubscription/v3/__init__.py
up_python-0.2.0.dev0.dist-info/LICENSE
up_python-0.2.0.dev0.dist-info/METADATA
up_python-0.2.0.dev0.dist-info/NOTICE.adoc
up_python-0.2.0.dev0.dist-info/WHEEL
up_python-0.2.0.dev0.dist-info/RECORD
