Metadata-Version: 2.1
Name: up-python
Version: 0.2.0.dev0
Summary: Language specific uProtocol library for building and using UUri, UUID, UAttributes, UTransport, and more.
Home-page: https://github.com/eclipse-uprotocol/up-python
License: The Apache License, Version 2.0
Author: Neelam Kushwah
Author-email: neelam.kushwah@gm.com
Requires-Python: >=3.8,<4.0
Classifier: License :: Other/Proprietary License
Classifier: Programming Language :: Python :: 3
Classifier: Programming Language :: Python :: 3.8
Classifier: Programming Language :: Python :: 3.9
Classifier: Programming Language :: Python :: 3.10
Classifier: Programming Language :: Python :: 3.11
Classifier: Programming Language :: Python :: 3.12
Requires-Dist: cloudevents
Requires-Dist: coverage (>=6.5.0)
Requires-Dist: gitpython (>=3.1.41)
Requires-Dist: googleapis-common-protos (>=1.56.4)
Requires-Dist: protobuf (==4.24.2)
Requires-Dist: pytest (>=6.2.5)
Requires-Dist: pytest-asyncio (>=0.15.1)
Requires-Dist: pytest-timeout (>=1.4.2)
Project-URL: Repository, https://github.com/eclipse-uprotocol/up-python
